sestertii/__init__.py
sestertii/dummy_function.py
tests/__init__.py
tests/dummy_test.py
Sestertii-0.0.3.dist-info/LICENSE
Sestertii-0.0.3.dist-info/METADATA
Sestertii-0.0.3.dist-info/WHEEL
Sestertii-0.0.3.dist-info/top_level.txt
Sestertii-0.0.3.dist-info/RECORD
