Metadata-Version: 2.1
Name: Sestertii
Version: 0.0.3
Summary: A personalized stock trading dashboard
Home-page: https://github.com/harishk1908/sestertii
Author: Harish Kumar
Author-email: harishk1908@gmail.com
License: UNKNOWN
Platform: UNKNOWN
Classifier: Programming Language :: Python :: 3
Classifier: License :: OSI Approved :: MIT License
Classifier: Operating System :: OS Independent
Requires-Dist: numpy (==1.18.1)
